{
  "fetched_at": "2026-07-16 01:28:04 UTC",
  "source": "yfinance-computed",
  "health": "amber",
  "primary_ok": false,
  "is_stale": false,
  "indicators_stale": true,
  "ta_valid": 0,
  "ind_valid": 14,
  "price_valid": 14,
  "universe_size": 15,
  "btc": {
    "last": 64586.1,
    "day_pct": -0.2628007661959586,
    "src": "tradingview"
  },
  "eth": {
    "last": 1916.17,
    "day_pct": -0.07769886215491845,
    "src": "tradingview"
  },
  "eth_weekly_close": 1915.1300048828125,
  "tickers": {
    "CIFR": {
      "last": 19.8700008392334,
      "src": "yfinance",
      "day_pct": 0.0,
      "p5": -9.061782643791172,
      "p1m": -18.89795575823102,
      "rsi_d": 40.48011598886624,
      "rsi_w": 50.74724670989089,
      "macd_dir": "down",
      "ma_stack": 2,
      "setup": 45,
      "pivot": 50,
      "hype": "Building",
      "sent_label": "Heavy bullish",
      "stk_bull": 13,
      "stk_bear": 0,
      "stk_total": 30,
      "stk_dir_total": 13,
      "diverge": true,
      "diverge_type": "crowd heavy-long into bearish MACD",
      "reddit": "no-data",
      "si": {
        "si_pct": 16.11,
        "dtc": 2.32,
        "asof": "2026-06-30",
        "fetched_at": "2026-07-16",
        "carried": false,
        "age_days": 16,
        "stale": true
      },
      "closes": [
        23.260000228881836,
        22.110000610351562,
        20.084999084472656,
        19.8700008392334,
        19.8700008392334
      ],
      "trail_high": 30.139999389648438
    },
    "IREN": {
      "last": 38.279998779296875,
      "src": "yfinance",
      "day_pct": -0.8033204769765323,
      "p5": -10.987099573220494,
      "p1m": -35.954494753020214,
      "rsi_d": 35.56469245869437,
      "rsi_w": 43.70200461572079,
      "macd_dir": "down",
      "ma_stack": 1,
      "setup": 35,
      "pivot": 20,
      "hype": "Building",
      "sent_label": "Heavy bullish",
      "stk_bull": 8,
      "stk_bear": 1,
      "stk_total": 30,
      "stk_dir_total": 9,
      "diverge": true,
      "diverge_type": "crowd heavy-long into bearish MACD",
      "reddit": "no-data",
      "si": {
        "si_pct": 21.97,
        "dtc": 1.89,
        "asof": "2026-06-30",
        "fetched_at": "2026-07-16",
        "carried": false,
        "age_days": 16,
        "stale": true
      },
      "closes": [
        41.720001220703125,
        41.13999938964844,
        38.97999954223633,
        38.59000015258789,
        38.279998779296875
      ],
      "trail_high": 70.70700073242188
    },
    "SLNH": {
      "last": 1.1100000143051147,
      "src": "yfinance",
      "day_pct": -0.8928562875609058,
      "p5": -14.615380383101995,
      "p1m": -25.0,
      "rsi_d": 36.524310376234055,
      "rsi_w": 45.36776851913851,
      "macd_dir": "down",
      "ma_stack": 0,
      "setup": 35,
      "pivot": 20,
      "hype": "Building",
      "sent_label": "Bullish lean",
      "stk_bull": 12,
      "stk_bear": 3,
      "stk_total": 30,
      "stk_dir_total": 15,
      "diverge": true,
      "diverge_type": "crowd heavy-long into bearish MACD",
      "reddit": "no-data",
      "si": {
        "si_pct": 23.68,
        "dtc": 2.05,
        "asof": "2026-06-30",
        "fetched_at": "2026-07-16",
        "carried": false,
        "age_days": 16,
        "stale": true
      },
      "closes": [
        1.2999999523162842,
        1.2599999904632568,
        1.1200000047683716,
        1.1200000047683716,
        1.1100000143051147
      ],
      "trail_high": 2.140000104904175
    },
    "BGDE": {
      "last": 6.360000133514404,
      "src": "yfinance",
      "day_pct": -5.0746221705941235,
      "p5": -11.173180599813204,
      "p1m": -14.054053357432938,
      "rsi_d": 39.85213747851948,
      "rsi_w": 47.927737233218856,
      "macd_dir": "down",
      "ma_stack": 0,
      "setup": 35,
      "pivot": 20,
      "hype": "Building",
      "sent_label": "Heavy bullish",
      "stk_bull": 7,
      "stk_bear": 0,
      "stk_total": 30,
      "stk_dir_total": 7,
      "diverge": true,
      "diverge_type": "crowd heavy-long into bearish MACD",
      "reddit": "no-data",
      "si": {
        "si_pct": 5.65,
        "dtc": 2.13,
        "asof": "2026-06-30",
        "fetched_at": "2026-07-16",
        "carried": false,
        "age_days": 16,
        "stale": true
      },
      "closes": [
        7.769999980926514,
        7.429999828338623,
        6.889999866485596,
        6.699999809265137,
        6.360000133514404
      ],
      "trail_high": 11.6899995803833
    },
    "BTBT": {
      "last": 1.5800000429153442,
      "src": "yfinance",
      "day_pct": -4.242420257834523,
      "p5": -5.389216555815112,
      "p1m": -9.195400330141224,
      "rsi_d": 38.216131823486585,
      "rsi_w": 38.904073244441044,
      "macd_dir": "down",
      "ma_stack": 0,
      "setup": 35,
      "pivot": 20,
      "hype": "Building",
      "sent_label": "Heavy bullish",
      "stk_bull": 8,
      "stk_bear": 0,
      "stk_total": 30,
      "stk_dir_total": 8,
      "diverge": true,
      "diverge_type": "crowd heavy-long into bearish MACD",
      "reddit": "no-data",
      "si": {
        "si_pct": 15.22,
        "dtc": 2.15,
        "asof": "2026-06-30",
        "fetched_at": "2026-07-16",
        "carried": false,
        "age_days": 16,
        "stale": true
      },
      "closes": [
        1.6799999475479126,
        1.690000057220459,
        1.6399999856948853,
        1.649999976158142,
        1.5800000429153442
      ],
      "trail_high": 2.390000104904175
    },
    "CORZ": {
      "last": 22.719999313354492,
      "src": "yfinance",
      "day_pct": 2.8519653979848236,
      "p5": -3.319151858065994,
      "p1m": -17.681163045894742,
      "rsi_d": 41.48520296861265,
      "rsi_w": 52.94218444147495,
      "macd_dir": "down",
      "ma_stack": 2,
      "setup": 45,
      "pivot": 55,
      "hype": "Building",
      "sent_label": "Heavy bullish",
      "stk_bull": 11,
      "stk_bear": 1,
      "stk_total": 30,
      "stk_dir_total": 12,
      "diverge": true,
      "diverge_type": "crowd heavy-long into bearish MACD",
      "reddit": "no-data",
      "si": {
        "si_pct": 24.6,
        "dtc": 5.93,
        "asof": "2026-06-30",
        "fetched_at": "2026-07-16",
        "carried": false,
        "age_days": 16,
        "stale": true
      },
      "closes": [
        23.739999771118164,
        23.489999771118164,
        22.709999084472656,
        22.09000015258789,
        22.719999313354492
      ],
      "trail_high": 30.459999084472656
    },
    "HUT": {
      "last": 103.02999877929688,
      "src": "yfinance",
      "day_pct": 4.779819852253708,
      "p5": -2.9026499041921783,
      "p1m": -13.318190938723628,
      "rsi_d": 45.81847199873585,
      "rsi_w": 60.28466719557905,
      "macd_dir": "down",
      "ma_stack": 2,
      "setup": 55,
      "pivot": 60,
      "hype": "Building",
      "sent_label": "Heavy bullish",
      "stk_bull": 8,
      "stk_bear": 1,
      "stk_total": 30,
      "stk_dir_total": 9,
      "diverge": true,
      "diverge_type": "crowd heavy-long into bearish MACD",
      "reddit": "no-data",
      "si": {
        "si_pct": 12.43,
        "dtc": 3.32,
        "asof": "2026-06-30",
        "fetched_at": "2026-07-16",
        "carried": false,
        "age_days": 16,
        "stale": true
      },
      "closes": [
        106.22000122070312,
        102.22000122070312,
        99.16999816894531,
        98.33000183105469,
        103.02999877929688
      ],
      "trail_high": 140.8000030517578
    },
    "CLSK": {
      "last": 14.130000114440918,
      "src": "yfinance",
      "day_pct": 5.055764422445264,
      "p5": 13.951617331708398,
      "p1m": -14.259705661839572,
      "rsi_d": 48.065746626771734,
      "rsi_w": 51.20918931669825,
      "macd_dir": "down",
      "ma_stack": 2,
      "setup": 55,
      "pivot": 50,
      "hype": "Building",
      "sent_label": "Heavy bullish",
      "stk_bull": 13,
      "stk_bear": 1,
      "stk_total": 30,
      "stk_dir_total": 14,
      "diverge": true,
      "diverge_type": "crowd heavy-long into bearish MACD",
      "reddit": "no-data",
      "si": {
        "si_pct": 42.88,
        "dtc": 3.66,
        "asof": "2026-06-30",
        "fetched_at": "2026-07-16",
        "carried": false,
        "age_days": 16,
        "stale": true
      },
      "closes": [
        12.890000343322754,
        12.850000381469727,
        12.359999656677246,
        13.449999809265137,
        14.130000114440918
      ],
      "trail_high": 19.170000076293945
    },
    "APLD": {
      "last": 29.030000686645508,
      "src": "yfinance",
      "day_pct": 1.9669876599833103,
      "p5": -7.665393786496466,
      "p1m": -32.01405112891362,
      "rsi_d": 30.983185044063845,
      "rsi_w": 43.90335318783784,
      "macd_dir": "down",
      "ma_stack": 1,
      "setup": 20,
      "pivot": 20,
      "hype": "Building",
      "sent_label": "Heavy bullish",
      "stk_bull": 15,
      "stk_bear": 1,
      "stk_total": 30,
      "stk_dir_total": 16,
      "diverge": true,
      "diverge_type": "crowd heavy-long into bearish MACD",
      "reddit": "no-data",
      "si": {
        "si_pct": 26.97,
        "dtc": 4.17,
        "asof": "2026-06-30",
        "fetched_at": "2026-07-16",
        "carried": false,
        "age_days": 16,
        "stale": true
      },
      "closes": [
        32.290000915527344,
        31.149999618530273,
        28.84000015258789,
        28.469999313354492,
        29.030000686645508
      ],
      "trail_high": 50.724998474121094
    },
    "MARA": {
      "last": 12.289999961853027,
      "src": "yfinance",
      "day_pct": 1.0690799019095865,
      "p5": 2.24625202834301,
      "p1m": -12.713067979775062,
      "rsi_d": 43.622410144606874,
      "rsi_w": 47.43761362858212,
      "macd_dir": "down",
      "ma_stack": 2,
      "setup": 45,
      "pivot": 50,
      "hype": "Building",
      "sent_label": "Bullish lean",
      "stk_bull": 11,
      "stk_bear": 4,
      "stk_total": 30,
      "stk_dir_total": 15,
      "diverge": true,
      "diverge_type": "crowd heavy-long into bearish MACD",
      "reddit": "no-data",
      "si": {
        "si_pct": 32.14,
        "dtc": 2.41,
        "asof": "2026-06-30",
        "fetched_at": "2026-07-16",
        "carried": false,
        "age_days": 16,
        "stale": true
      },
      "closes": [
        13.220000267028809,
        12.600000381469727,
        12.1899995803833,
        12.15999984741211,
        12.289999961853027
      ],
      "trail_high": 16.43000030517578
    },
    "RIOT": {
      "last": 20.100000381469727,
      "src": "yfinance",
      "day_pct": -0.4457659742805542,
      "p5": -4.694166732837523,
      "p1m": -24.46448733394384,
      "rsi_d": 31.92851006264928,
      "rsi_w": 49.482101807098545,
      "macd_dir": "down",
      "ma_stack": 2,
      "setup": 30,
      "pivot": 50,
      "hype": "Building",
      "sent_label": "Bullish lean",
      "stk_bull": 6,
      "stk_bear": 2,
      "stk_total": 30,
      "stk_dir_total": 8,
      "diverge": true,
      "diverge_type": "crowd heavy-long into bearish MACD",
      "reddit": "no-data",
      "si": {
        "si_pct": 15.52,
        "dtc": 3.41,
        "asof": "2026-06-30",
        "fetched_at": "2026-07-16",
        "carried": false,
        "age_days": 16,
        "stale": true
      },
      "closes": [
        21.510000228881836,
        20.96500015258789,
        20.190000534057617,
        20.190000534057617,
        20.100000381469727
      ],
      "trail_high": 30.31999969482422
    },
    "BTDR": {
      "last": 12.569999694824219,
      "src": "yfinance",
      "day_pct": 1.69902948203986,
      "p5": 0.07961206109436958,
      "p1m": -29.50084268866625,
      "rsi_d": 38.41823375327408,
      "rsi_w": 47.25899787456859,
      "macd_dir": "down",
      "ma_stack": 1,
      "setup": 35,
      "pivot": 30,
      "hype": "Building",
      "sent_label": "Mixed",
      "stk_bull": 6,
      "stk_bear": 5,
      "stk_total": 30,
      "stk_dir_total": 11,
      "diverge": false,
      "diverge_type": "",
      "reddit": "no-data",
      "si": {
        "si_pct": 32.07,
        "dtc": 5.1,
        "asof": "2026-06-30",
        "fetched_at": "2026-07-16",
        "carried": false,
        "age_days": 16,
        "stale": true
      },
      "closes": [
        14.329999923706055,
        13.289999961853027,
        12.130000114440918,
        12.359999656677246,
        12.569999694824219
      ],
      "trail_high": 20.719999313354492
    },
    "BITF": {
      "last": null,
      "src": "none",
      "day_pct": null,
      "p5": null,
      "p1m": null,
      "rsi_d": null,
      "rsi_w": null,
      "macd_dir": null,
      "ma_stack": null,
      "setup": null,
      "pivot": null,
      "hype": "Quiet",
      "sent_label": "Quiet",
      "stk_bull": 0,
      "stk_bear": 0,
      "stk_total": 0,
      "stk_dir_total": 0,
      "diverge": null,
      "diverge_type": "",
      "reddit": "no-data",
      "si": null,
      "closes": [],
      "trail_high": null
    },
    "HIVE": {
      "last": 3.200000047683716,
      "src": "yfinance",
      "day_pct": 0.6289302046118772,
      "p5": -1.2345667202249944,
      "p1m": -14.209114441812254,
      "rsi_d": 41.711695989249264,
      "rsi_w": 50.5156303302554,
      "macd_dir": "down",
      "ma_stack": 1,
      "setup": 35,
      "pivot": 30,
      "hype": "Building",
      "sent_label": "Heavy bullish",
      "stk_bull": 13,
      "stk_bear": 1,
      "stk_total": 30,
      "stk_dir_total": 14,
      "diverge": true,
      "diverge_type": "crowd heavy-long into bearish MACD",
      "reddit": "no-data",
      "si": {
        "si_pct": 16.07,
        "dtc": 2.5,
        "asof": "2026-06-30",
        "fetched_at": "2026-07-16",
        "carried": false,
        "age_days": 16,
        "stale": true
      },
      "closes": [
        3.359999895095825,
        3.3499999046325684,
        3.190000057220459,
        3.180000066757202,
        3.200000047683716
      ],
      "trail_high": 5.340000152587891
    },
    "WULF": {
      "last": 19.3700008392334,
      "src": "yfinance",
      "day_pct": -0.20607423231919775,
      "p5": -15.155493193321856,
      "p1m": -25.671522501188438,
      "rsi_d": 35.74023912585983,
      "rsi_w": 49.042697304976635,
      "macd_dir": "down",
      "ma_stack": 2,
      "setup": 45,
      "pivot": 55,
      "hype": "Building",
      "sent_label": "Heavy bullish",
      "stk_bull": 17,
      "stk_bear": 0,
      "stk_total": 30,
      "stk_dir_total": 17,
      "diverge": true,
      "diverge_type": "crowd heavy-long into bearish MACD",
      "reddit": "no-data",
      "si": {
        "si_pct": 24.87,
        "dtc": 2.47,
        "asof": "2026-06-30",
        "fetched_at": "2026-07-16",
        "carried": false,
        "age_days": 16,
        "stale": true
      },
      "closes": [
        23.200000762939453,
        21.969999313354492,
        20.889999389648438,
        19.40999984741211,
        19.3700008392334
      ],
      "trail_high": 29.84000015258789
    }
  }
}